koverage/CITATION
koverage/VERSION
koverage/__init__.py
koverage/__main__.py
koverage/config/config.yaml
koverage/config/system_config.yaml
koverage/config/profile/config.yaml
koverage/scripts/__init__.py
koverage/scripts/combineCoverage.py
koverage/scripts/combineKmerCoverage.py
koverage/scripts/kmerScreen.py
koverage/scripts/koverageReport.py
koverage/scripts/minimapWrapper.py
koverage/scripts/refSampleKmer.py
koverage/scripts/sampleCoverage.py
koverage/test_data/ref.fa
koverage/test_data/reads/A13-04-182-06_TAGCTT_R1.fastq.gz
koverage/test_data/reads/A13-04-182-06_TAGCTT_R2.fastq.gz
koverage/test_data/reads/A13-151-169-06_ATGTCA_R1.fastq.gz
koverage/test_data/reads/A13-151-169-06_ATGTCA_R2.fastq.gz
koverage/test_data/refs/ref1.fa.gz
koverage/test_data/refs/ref2.fa.gz
koverage/test_data/refs/ref3.fa.gz
koverage/test_data/refs/ref4.fa.gz
koverage/test_data/refs/refs.tsv
koverage/workflow/Snakefile
koverage/workflow/__init__.py
koverage/workflow/envs/coverm.yaml
koverage/workflow/envs/jellyfish.yaml
koverage/workflow/envs/minimap.yaml
koverage/workflow/envs/zstd.yaml
koverage/workflow/rules/__init__.py
koverage/workflow/rules/combine_refs.smk
koverage/workflow/rules/coverage.smk
koverage/workflow/rules/coverm.smk
koverage/workflow/rules/kmer_coverage.smk
koverage/workflow/rules/preflight.smk
koverage/workflow/rules/reports.smk
koverage-0.1.11.data/data/README.md
koverage-0.1.11.dist-info/LICENSE
koverage-0.1.11.dist-info/METADATA
koverage-0.1.11.dist-info/WHEEL
koverage-0.1.11.dist-info/entry_points.txt
koverage-0.1.11.dist-info/top_level.txt
koverage-0.1.11.dist-info/RECORD
