Metadata-Version: 2.1
Name: koverage
Version: 0.1.11
Summary: Quickly get coverage statistics given reads and an assembly
Home-page: https://github.com/beardymcjohnface/Koverage
Author: Michael Roach
Author-email: beardymcjohnface@gmail.com
Requires-Python: >=3.10
License-File: LICENSE
Requires-Dist: snaketool-utils >=0.0.5
Requires-Dist: metasnek >=0.0.8
Requires-Dist: snakemake <8,>=7.29
Requires-Dist: pulp <2.8
Requires-Dist: pyyaml >=6.0
Requires-Dist: Click >=8.1.3
Requires-Dist: zstandard >=0.21.0
Requires-Dist: numpy >=1.24.3
Requires-Dist: datapane >=0.16.7
Requires-Dist: plotly >=5.15.0
